odoo/addons/survey_question_type_nps/README.rst
odoo/addons/survey_question_type_nps/__init__.py
odoo/addons/survey_question_type_nps/__manifest__.py
odoo/addons/survey_question_type_nps/i18n/it.po
odoo/addons/survey_question_type_nps/i18n/survey_question_type_nps.pot
odoo/addons/survey_question_type_nps/models/__init__.py
odoo/addons/survey_question_type_nps/models/survey_question.py
odoo/addons/survey_question_type_nps/models/survey_user_input_line.py
odoo/addons/survey_question_type_nps/readme/CONTRIBUTORS.rst
odoo/addons/survey_question_type_nps/readme/DESCRIPTION.rst
odoo/addons/survey_question_type_nps/static/description/icon.png
odoo/addons/survey_question_type_nps/static/description/index.html
odoo/addons/survey_question_type_nps/static/src/js/survey.js
odoo/addons/survey_question_type_nps/static/src/scss/parameters.scss
odoo/addons/survey_question_type_nps/static/src/scss/survey.scss
odoo/addons/survey_question_type_nps/templates/survey_template.xml
odoo/addons/survey_question_type_nps/tests/__init__.py
odoo/addons/survey_question_type_nps/tests/test_survey.py
odoo/addons/survey_question_type_nps/views/survey_question.xml
odoo14_addon_survey_question_type_nps-14.0.1.0.1.dev9.dist-info/METADATA
odoo14_addon_survey_question_type_nps-14.0.1.0.1.dev9.dist-info/WHEEL
odoo14_addon_survey_question_type_nps-14.0.1.0.1.dev9.dist-info/top_level.txt
odoo14_addon_survey_question_type_nps-14.0.1.0.1.dev9.dist-info/RECORD
